odoo/addons/account_reconcile_show_boolean/README.rst
odoo/addons/account_reconcile_show_boolean/__init__.py
odoo/addons/account_reconcile_show_boolean/__manifest__.py
odoo/addons/account_reconcile_show_boolean/i18n/account_reconcile_show_boolean.pot
odoo/addons/account_reconcile_show_boolean/i18n/it.po
odoo/addons/account_reconcile_show_boolean/readme/CONTRIBUTORS.rst
odoo/addons/account_reconcile_show_boolean/readme/DESCRIPTION.rst
odoo/addons/account_reconcile_show_boolean/readme/USAGE.rst
odoo/addons/account_reconcile_show_boolean/static/description/icon.png
odoo/addons/account_reconcile_show_boolean/static/description/icon.svg
odoo/addons/account_reconcile_show_boolean/static/description/index.html
odoo/addons/account_reconcile_show_boolean/views/account_account_view.xml
odoo14_addon_account_reconcile_show_boolean-14.0.1.0.1.dev4.dist-info/METADATA
odoo14_addon_account_reconcile_show_boolean-14.0.1.0.1.dev4.dist-info/WHEEL
odoo14_addon_account_reconcile_show_boolean-14.0.1.0.1.dev4.dist-info/top_level.txt
odoo14_addon_account_reconcile_show_boolean-14.0.1.0.1.dev4.dist-info/RECORD
